discord/ext/fslash/__init__.py
discord/ext/fslash/context.py
discord/ext/fslash/types_.py
discord_ext_fslash-0.2.1.dist-info/LICENSE
discord_ext_fslash-0.2.1.dist-info/METADATA
discord_ext_fslash-0.2.1.dist-info/WHEEL
discord_ext_fslash-0.2.1.dist-info/top_level.txt
discord_ext_fslash-0.2.1.dist-info/RECORD
