Metadata-Version: 2.1
Name: discord-ext-fslash
Version: 0.2.1
Summary: Force the discord.py command framework to correspond to the slashes.
Home-page: UNKNOWN
Author: tasuren
Author-email: tasuren@aol.com
License: MIT
Project-URL: Documentation, https://tasuren.github.io/discord-ext-fslash
Project-URL: Donate, https://www.buymeacoffee.com/tasuren
Project-URL: Source Code, https://github.com/tasuren/discord-ext-fslash
Project-URL: Chat, https://discord.gg/kfMwZUyGFG
Keywords: discord discord.py
Platform: UNKNOWN
Classifier: Programming Language :: Python :: 3.8
Classifier: Programming Language :: Python :: 3.9
Classifier: Programming Language :: Python :: 3.10
Classifier: Programming Language :: Python :: 3.11
Requires-Python: >=3.8.0
License-File: LICENSE
Requires-Dist: discord.py (>=2.0.0)
